uwwvb.py
wwvb/__init__.py
wwvb/__version__.py
wwvb/decode.py
wwvb/dut1table.py
wwvb/gen.py
wwvb/iersdata.json
wwvb/iersdata.json.license
wwvb/iersdata.py
wwvb/py.typed
wwvb/tz.py
wwvb/updateiers.py
wwvb/wwvbtk.py
wwvb-7.0.0.dist-info/METADATA
wwvb-7.0.0.dist-info/WHEEL
wwvb-7.0.0.dist-info/entry_points.txt
wwvb-7.0.0.dist-info/top_level.txt
wwvb-7.0.0.dist-info/RECORD
