Metadata-Version: 2.4
Name: wwvb
Version: 7.0.0
Summary: Generate WWVB timecodes for any desired time
Author-email: Jeff Epler <jepler@gmail.com>
Project-URL: Source, https://github.com/jepler/wwvbpy
Project-URL: Documentation, https://github.com/jepler/wwvbpy
Classifier: Programming Language :: Python :: 3
Classifier: Programming Language :: Python :: 3.9
Classifier: Programming Language :: Python :: 3.10
Classifier: Programming Language :: Python :: 3.11
Classifier: Programming Language :: Python :: Implementation :: PyPy
Classifier: Programming Language :: Python :: Implementation :: CPython
Classifier: License :: OSI Approved :: GNU General Public License v3 (GPLv3)
Classifier: Operating System :: OS Independent
Requires-Python: >=3.9
Requires-Dist: adafruit-circuitpython-datetime
Requires-Dist: beautifulsoup4
Requires-Dist: click
Requires-Dist: leapseconddata
Requires-Dist: platformdirs
Requires-Dist: python-dateutil
Requires-Dist: requests
Requires-Dist: tzdata
